djangosc/__init__.py
example_pkg/__init__.py
waynevanpython-0.0.4.dist-info/LICENSE
waynevanpython-0.0.4.dist-info/METADATA
waynevanpython-0.0.4.dist-info/WHEEL
waynevanpython-0.0.4.dist-info/top_level.txt
waynevanpython-0.0.4.dist-info/RECORD
